spdx3toopenvex/__init__.py
spdx3toopenvex/__main__.py
spdx3toopenvex/convert.py
spdx3toopenvex/main.py
spdx3toopenvex/version.py
spdx3toopenvex-0.0.1.dist-info/METADATA
spdx3toopenvex-0.0.1.dist-info/WHEEL
spdx3toopenvex-0.0.1.dist-info/entry_points.txt
spdx3toopenvex-0.0.1.dist-info/licenses/LICENSE
spdx3toopenvex-0.0.1.dist-info/RECORD
